pandoc_simplecite.py
pandoc_simplecite-0.0.4.dist-info/LICENSE
pandoc_simplecite-0.0.4.dist-info/METADATA
pandoc_simplecite-0.0.4.dist-info/WHEEL
pandoc_simplecite-0.0.4.dist-info/entry_points.txt
pandoc_simplecite-0.0.4.dist-info/top_level.txt
pandoc_simplecite-0.0.4.dist-info/RECORD
