Metadata-Version: 2.1
Name: pandoc-simplecite
Version: 0.0.4
Summary: Simple citation filter for pandoc
Home-page: https://gitlab.com/walter76/pandoc-simplecite
Author: Walter Stocker
Author-email: wrstocke@googlemail.com
License: MIT
Keywords: pandoc cite simple filter
Platform: UNKNOWN
Classifier: Development Status :: 4 - Beta
Classifier: Intended Audience :: End Users/Desktop
Classifier: Environment :: Console
Classifier: License :: OSI Approved :: MIT License
Classifier: Programming Language :: Python
Classifier: Topic :: Software Development :: Documentation
Classifier: Topic :: Text Processing :: Filters
